[{"ID":"00000000-0000-0000-0000-000000000000","Nombre":"Haien Feng","Telefono":"8095558888","Compañia":"Altice","Posición":"Gerente","Imagen":"C:\\Users\\alber\\source\\Porgrmacion 2 repos\\PF 2\\RegistrodeTelefonia-main\\Form1\\bin\\Debug\\net6.0-windows\\\\usuario.png","Fecha":"2022-07-18T16:15:25.5276201-04:00"},{"ID":"00000000-0000-0000-0000-000000000000","Nombre":"Rodolfo Pena","Telefono":"8099967381","Compañia":"Claro","Posición":"Chairman","Imagen":"C:\\Users\\alber\\OneDrive\\Pictures\\Screenshots\\Screenshot (1).png","Fecha":"2022-07-18T16:15:58.7628813-04:00"}]